{"skeleton":{"hash":"sCxsDdJ3KHGiLu1BFIKOWjjsCA0","spine":"3.8.95","x":-258.08,"y":-11.09,"width":589,"height":915.98,"fps":24,"images":"./images/","audio":"/Users/annakotovskova/Desktop/WORK/SpineSandboxer/G-M/Gifts_001/g_sunflower"},"bones":[{"name":"root"},{"name":"bone3","parent":"root","x":61.35,"y":258.07,"color":"eb03f5ff"},{"name":"bone4","parent":"bone3","length":79.63,"rotation":107.72,"x":-1.56,"y":0.78,"color":"eb03f5ff"},{"name":"leafR","parent":"bone4","rotation":-107.72,"x":35.92,"y":-17.84,"color":"4dea00ff"},{"name":"leafL","parent":"bone4","rotation":-107.72,"x":79.44,"y":8.45,"color":"4dea00ff"},{"name":"bone5","parent":"bone4","length":112.94,"rotation":-13.35,"x":79.63,"color":"eb03f5ff"},{"name":"bone6","parent":"bone5","length":125.9,"rotation":-4.01,"x":112.94,"color":"eb03f5ff"},{"name":"bone7","parent":"bone6","length":58.13,"rotation":-5.76,"x":125.9,"color":"eb03f5ff"},{"name":"leafL2","parent":"leafL","length":107.9,"rotation":-158.57,"x":-155.71,"y":19.54,"color":"4dea00ff"},{"name":"leafR2","parent":"leafR","length":100,"rotation":9.9,"x":84.94,"y":62.42,"color":"4dea00ff"},{"name":"leafR3","parent":"leafR2","length":35.48,"rotation":-16.93,"x":100.81,"y":-1.36,"color":"4dea00ff"}],"slots":[{"name":"stroke","bone":"root","attachment":"stroke"},{"name":"gorshok","bone":"root","attachment":"gorshok"},{"name":"leaf_right","bone":"leafR","attachment":"leaf_right"},{"name":"Stebel","bone":"root","attachment":"Stebel"},{"name":"groundup","bone":"root","attachment":"groundup"},{"name":"leaf_left","bone":"leafL","attachment":"leaf_left"},{"name":"head","bone":"bone7","attachment":"head"}],"skins":[{"name":"default","attachments":{"Stebel":{"Stebel":{"type":"mesh","uvs":[0.50132,0.38341,0.66641,0.72412,1,0.90856,1,1,0.32401,1,0,0.60514,0.09858,0.37491,0,0,0.36069,0,0.12224,0.75369],"triangles":[6,8,0,0,5,6,5,0,1,5,9,4,9,5,1,2,9,1,2,4,9,4,2,3,6,7,8],"vertices":[1,6,-1,-18.96,1,1,5,6.45,-22.39,1,1,2,20.22,-28.39,1,1,2,-6.25,-19.9,1,1,2,8.19,25.16,1,1,5,46.11,21.34,1,1,6,1.78,9.21,1,1,1,-50.43,304.95,1,1,1,-25.18,304.93,1,1,5,0.43,16.29,1],"hull":9,"edges":[14,16,16,0,0,2,6,4,2,4,10,18,6,8,18,8,8,10,18,2,10,12,12,0,12,14],"width":70,"height":304}},"gorshok":{"gorshok":{"x":94.56,"y":209.41,"width":357,"height":441}},"groundup":{"groundup":{"x":65.05,"y":337.28,"width":242,"height":185}},"head":{"head":{"x":59.04,"y":-6.11,"rotation":-84.6,"width":575,"height":532}},"leaf_left":{"leaf_left":{"type":"mesh","uvs":[1,1,0.5893,1,0.41337,1,0.25981,0.80012,0,0.92868,0,0.83834,0.22552,0.3936,0.37312,0.16427,0.53265,0,1,0],"triangles":[1,2,7,3,7,2,3,6,7,5,6,3,4,5,3,1,7,8,1,8,9,1,9,0],"vertices":[2,4,15.67,-35.03,0.99975,8,-139.59,113.42,0.00025,2,4,-97.27,-35.03,0.34899,8,-34.46,72.15,0.65101,2,4,-145.65,-35.03,0.07674,8,10.58,54.47,0.92326,2,4,-187.88,-11.45,0.00091,8,41.27,17.08,0.99909,1,8,113.32,5.09,1,1,8,109.42,-4.83,1,1,8,32.52,-31.02,1,2,4,-156.72,63.58,0.04716,8,-15.16,-41.37,0.95284,2,4,-112.85,82.97,0.26554,8,-63.08,-43.38,0.73446,1,4,15.67,82.97,1],"hull":10,"edges":[0,18,10,12,12,14,0,2,14,2,16,18,14,16,8,10,8,6,2,4,6,4],"width":275,"height":118}},"leaf_right":{"leaf_right":{"type":"mesh","uvs":[1,0.1525,1,0.39584,0.90253,0.34054,0.83617,0.41428,0.76243,0.68711,0.56367,0.83243,0.35133,1,0,1,0,0,0.6315,0.00001],"triangles":[2,0,1,2,9,0,9,5,6,5,9,4,4,9,3,3,9,2,6,7,8,9,6,8],"vertices":[2,9,95.38,-8.8,0,10,38.43,11.75,1,1,10,41.86,-16.02,1,2,9,74.55,-21.93,0.17002,10,26.61,-9.41,0.82998,3,3,228.56,56.7,0.00036,9,86.85,-25.75,0.76548,10,40.54,-7.51,0.23416,3,3,217.25,28.85,0.02592,9,74.21,-52.45,0.95463,10,42.36,-37.53,0.01944,3,3,167.54,15.01,0.09975,9,23.69,-61.1,0.89897,10,-0.68,-65.61,0.00128,1,3,74.88,-12.09,1,1,3,-5.93,-12.09,1,1,3,-5.93,102.91,1,2,3,185.18,115.15,0.21986,9,47.2,29.36,0.78014],"hull":10,"edges":[14,16,16,18,18,0,0,2,2,4,4,6,6,8,12,14,8,10,10,12,18,10],"width":230,"height":115}},"stroke":{"stroke":{"x":36.42,"y":448.4,"width":589,"height":913}}}}],"animations":{"animation":{"slots":{"stroke":{"color":[{"time":8.5833,"color":"ffffff00"},{"time":9.75,"color":"ffffffff"}],"attachment":[{"name":null},{"time":8.5833,"name":"stroke"}]}},"bones":{"bone3":{"rotate":[{"time":5,"curve":0.304,"c2":0.5},{"time":5.6667,"angle":-0.7,"curve":"stepped"},{"time":5.8333,"angle":-0.7,"curve":0.313,"c2":0.5,"c4":0.99},{"time":6.625,"curve":"stepped"},{"time":6.7917,"curve":0.308,"c2":0.5},{"time":7.4167,"angle":-0.7,"curve":"stepped"},{"time":7.5833,"angle":-0.7,"curve":0.38,"c2":0.5,"c4":0.99},{"time":8.375}]},"bone7":{"rotate":[{"time":5,"curve":0.304,"c2":0.5},{"time":5.6667,"angle":-0.78,"curve":"stepped"},{"time":5.8333,"angle":-0.78,"curve":0.313,"c2":0.5,"c4":0.99},{"time":6.625,"angle":1.88,"curve":"stepped"},{"time":6.7917,"angle":1.88,"curve":0.308,"c2":0.5},{"time":7.4167,"angle":-0.78,"curve":"stepped"},{"time":7.5833,"angle":-0.78,"curve":0.38,"c2":0.5,"c4":0.99},{"time":8.375}],"translate":[{"time":5.8333,"curve":0.313,"c2":0.5,"c4":0.99},{"time":6.625,"y":25.75,"curve":"stepped"},{"time":6.7917,"y":25.75,"curve":0.308,"c2":0.5},{"time":7.4167}]},"bone6":{"rotate":[{"time":5,"curve":0.304,"c2":0.5},{"time":5.6667,"angle":-6.11,"curve":"stepped"},{"time":5.8333,"angle":-6.11,"curve":0.313,"c2":0.5,"c4":0.99},{"time":6.625,"angle":1.88,"curve":"stepped"},{"time":6.7917,"angle":1.88,"curve":0.308,"c2":0.5},{"time":7.4167,"angle":-6.11,"curve":"stepped"},{"time":7.5833,"angle":-6.11,"curve":0.38,"c2":0.5,"c4":0.99},{"time":8.375}],"translate":[{"time":5.3333},{"time":5.6667,"x":-11.55,"y":0.47,"curve":"stepped"},{"time":5.8333,"x":-11.55,"y":0.47,"curve":0.313,"c2":0.5,"c4":0.99},{"time":6.625,"curve":"stepped"},{"time":6.7917,"curve":0.308,"c2":0.5},{"time":7.4167,"x":-11.55,"y":0.47,"curve":"stepped"},{"time":7.5833,"x":-11.55,"y":0.47,"curve":0.38,"c2":0.5,"c4":0.99},{"time":8.375}]},"bone5":{"rotate":[{"time":5,"curve":0.304,"c2":0.5},{"time":5.6667,"angle":-11.71,"curve":"stepped"},{"time":5.8333,"angle":-11.71,"curve":0.313,"c2":0.5,"c4":0.99},{"time":6.625,"angle":1.88,"curve":"stepped"},{"time":6.7917,"angle":1.88,"curve":0.308,"c2":0.5},{"time":7.4167,"angle":-11.71,"curve":"stepped"},{"time":7.5833,"angle":-11.71,"curve":0.38,"c2":0.5,"c4":0.99},{"time":8.375}]},"bone4":{"rotate":[{"time":5,"curve":0.304,"c2":0.5},{"time":5.6667,"angle":-9.61,"curve":"stepped"},{"time":5.8333,"angle":-9.61,"curve":0.313,"c2":0.5,"c4":0.99},{"time":6.625,"curve":"stepped"},{"time":6.7917,"curve":0.308,"c2":0.5},{"time":7.4167,"angle":-9.61,"curve":"stepped"},{"time":7.5833,"angle":-9.61,"curve":0.38,"c2":0.5,"c4":0.99},{"time":8.375}]},"leafL2":{"rotate":[{"time":5.3333},{"time":5.6667,"angle":12.06,"curve":"stepped"},{"time":5.8333,"angle":12.06,"curve":0.62,"c2":0.51},{"time":6.3333,"curve":"stepped"},{"time":6.7917},{"time":7.4167,"angle":12.06,"curve":"stepped"},{"time":7.5833,"angle":12.06,"curve":0.62,"c2":0.51},{"time":8.375}],"translate":[{"time":5.3333},{"time":5.6667,"x":4.46,"y":-28.68,"curve":"stepped"},{"time":5.8333,"x":4.46,"y":-28.68,"curve":0.62,"c2":0.51},{"time":6.3333,"curve":"stepped"},{"time":6.7917},{"time":7.4167,"x":4.46,"y":-28.68,"curve":"stepped"},{"time":7.5833,"x":4.46,"y":-28.68,"curve":0.62,"c2":0.51},{"time":8.375}]},"leafR2":{"rotate":[{"time":5.3333},{"time":5.6667,"angle":-17.36,"curve":"stepped"},{"time":5.8333,"angle":-17.36,"curve":0.62,"c2":0.51},{"time":6.3333,"curve":"stepped"},{"time":6.7917},{"time":7.4167,"angle":-17.36,"curve":"stepped"},{"time":7.5833,"angle":-17.36,"curve":0.62,"c2":0.51},{"time":8.375}],"translate":[{"time":5.3333},{"time":5.6667,"y":-6.47,"curve":"stepped"},{"time":5.8333,"y":-6.47,"curve":0.62,"c2":0.51},{"time":6.3333,"curve":"stepped"},{"time":6.7917},{"time":7.4167,"y":-6.47,"curve":"stepped"},{"time":7.5833,"y":-6.47,"curve":0.62,"c2":0.51},{"time":8.375}]},"leafR3":{"rotate":[{"time":5.3333},{"time":5.6667,"angle":-31.04,"curve":"stepped"},{"time":5.8333,"angle":-31.04,"curve":0.62,"c2":0.51},{"time":6.3333,"curve":"stepped"},{"time":6.7917},{"time":7.4167,"angle":-31.04,"curve":"stepped"},{"time":7.5833,"angle":-31.04,"curve":0.62,"c2":0.51},{"time":8.375}],"translate":[{"time":5.3333},{"time":5.6667,"x":-10.74,"y":4.1,"curve":"stepped"},{"time":5.8333,"x":-10.74,"y":4.1,"curve":0.62,"c2":0.51},{"time":6.3333,"curve":"stepped"},{"time":6.7917},{"time":7.4167,"x":-10.74,"y":4.1,"curve":"stepped"},{"time":7.5833,"x":-10.74,"y":4.1,"curve":0.62,"c2":0.51},{"time":8.375}]},"leafR":{"rotate":[{"time":6.0833,"curve":0.79,"c2":0.5},{"time":6.625,"angle":7.8,"curve":"stepped"},{"time":6.7917,"angle":7.8,"curve":0.018,"c3":0.071,"c4":0.65},{"time":7.4167}]},"leafL":{"rotate":[{"time":6.0833,"curve":0.616,"c2":0.5},{"time":6.625,"angle":-6,"curve":"stepped"},{"time":6.7917,"angle":-6,"curve":0.018,"c3":0.071,"c4":0.65},{"time":7.4167}]}}}},"__atlas":"s_sunflower_v2.png\nsize: 324,372\nformat: RGBA8888\nfilter: Linear,Linear\nrepeat: none\nstroke\n  rotate: false\n  xy: 8,8\n  size: 148,229\n  orig: 148,229\n  offset: 0,0\n  index: -1\nhead\n  rotate: false\n  xy: 172,8\n  size: 144,134\n  orig: 144,134\n  offset: 0,0\n  index: -1\ngorshok\n  rotate: false\n  xy: 8,253\n  size: 90,111\n  orig: 90,111\n  offset: 0,0\n  index: -1\nStebel\n  rotate: false\n  xy: 114,253\n  size: 18,76\n  orig: 18,76\n  offset: 0,0\n  index: -1\nleaf_left\n  rotate: false\n  xy: 172,158\n  size: 69,30\n  orig: 69,30\n  offset: 0,0\n  index: -1\ngroundup\n  rotate: false\n  xy: 148,253\n  size: 61,46\n  orig: 61,46\n  offset: 0,0\n  index: -1\nleaf_right\n  rotate: false\n  xy: 257,158\n  size: 58,29\n  orig: 58,29\n  offset: 0,0\n  index: -1\n"}