{"skeleton":{"hash":"ipKxJ0jlklHJYSG3M5iy+boRjqA","spine":"3.8.95","x":-51.93,"y":-27.1,"width":260,"height":852.73,"fps":24,"images":"./images/","audio":"/Users/annakotovskova/Desktop/WORK/SpineSandboxer/G-M/g_heinekenbottle"},"bones":[{"name":"root"},{"name":"bottle","parent":"root","x":64.03,"y":-10.9},{"name":"lid","parent":"bottle","x":56.54,"y":766.79}],"slots":[{"name":"shadow","bone":"bottle","attachment":"shadow"},{"name":"stroke","bone":"lid","attachment":"stroke"},{"name":"bottle","bone":"bottle","attachment":"bottle"},{"name":"Lid","bone":"lid","attachment":"Lid"}],"skins":[{"name":"default","attachments":{"Lid":{"Lid":{"x":-56.5,"y":27.5,"width":112,"height":69}},"bottle":{"bottle":{"x":0.54,"y":413.79,"width":233,"height":836}},"shadow":{"shadow":{"x":22.04,"y":31.29,"width":244,"height":95}},"stroke":{"stroke":{"x":-56.5,"y":26.73,"width":128,"height":86}}}}],"animations":{"animation":{"slots":{"Lid":{"color":[{"time":6.125,"color":"ffffffff"},{"time":6.25,"color":"ffffff00"}]},"stroke":{"color":[{"time":6.125,"color":"ffffffff"},{"time":6.25,"color":"ffffff00"}]}},"bones":{"lid":{"rotate":[{"time":5.2083},{"time":6.125,"angle":-100.76},{"time":6.25,"angle":-130.9}],"translate":[{"time":5.2083},{"time":6.125,"x":38.07,"y":79.95}]},"bottle":{"rotate":[{"time":5},{"time":5.0417,"angle":1},{"time":5.0833},{"time":5.125,"angle":-1},{"time":5.1667}]}}}},"__atlas":"s_heineken.png\nsize: 61,87\nformat: RGBA8888\nfilter: Linear,Linear\nrepeat: none\nbottle\n  rotate: false\n  xy: 4,4\n  size: 22,79\n  orig: 22,79\n  offset: 0,0\n  index: -1\nshadow\n  rotate: false\n  xy: 34,4\n  size: 23,9\n  orig: 23,9\n  offset: 0,0\n  index: -1\nstroke\n  rotate: false\n  xy: 34,21\n  size: 12,8\n  orig: 12,8\n  offset: 0,0\n  index: -1\nLid\n  rotate: false\n  xy: 34,37\n  size: 11,6\n  orig: 11,6\n  offset: 0,0\n  index: -1\n"}